{
  "id": "ez",
  "num": "Livro 26 · Antigo Testamento",
  "title": "Ezequiel",
  "abbr": "Ez · Profetas Maiores",
  "author": "Ezequiel, filho de Buzi (sacerdote-profeta)",
  "chars": [
    "Ezequiel",
    "Nabucodonosor",
    "O Príncipe de Tiro"
  ],
  "tags": [
    "Visões",
    "Glória de Deus",
    "Exílio",
    "Merkavah",
    "Ossos Secos",
    "Novo Templo"
  ],
  "body": "<p><strong>Contexto:</strong> Ezequiel profetizou entre os exilados na Babilônia (593–571 a.C.). Sacerdote antes de ser profeta, sua teologia é profundamente litúrgica e visionária. O livro é o mais simbólico dos profetas maiores e exerceu enorme influência sobre a literatura apocalíptica judaica e o Apocalipse de João.</p>\n<p><strong>A visão da <em>merkavah</em> (cap. 1):</strong> A carruagem divina — quatro criaturas viventes com asas e rodas dentro de rodas — é a visão de abertura. Representa a onipresença e mobilidade da glória de YHWH, que não está presa ao Templo de Jerusalém. A subsequente partida da glória divina do Templo (caps. 8–11) é o momento mais assustador do livro: Deus abandona o Templo corrompido antes que os babilônios o destruam.</p>\n<p><strong>Oráculos de julgamento e restauração:</strong> Os capítulos 4–24 contêm oráculos de julgamento dramatizados em ações simbólicas de Ezequiel. Os capítulos 25–32 são oráculos contra as nações. A parte final (caps. 33–48) é de esperança: a visão dos ossos secos que voltam à vida (cap. 37 — imagem da restauração de Israel e, para o NT, da ressurreição corporal), e a visão do novo Templo escatológico com um rio que flui do santuário vivificando o mar Morto (caps. 40–48).</p>",
  "verse": "\"Darei a vocês um coração novo e porei dentro de vocês um espírito novo.\" <cite>Ezequiel 36.26 — NAA</cite>",
  "translation": "NAA",
  "order": 26,
  "category": "mai",
  "cellAbbr": "Ez"
}